[{"episode_key":"Fnr4cgp4b_fs2","series_key":"xeh0","season_key":"nr4c","title":"第1話 ⑥TVerコンマステスト かためのプリン／ホットケーキ","title_kana":"カタメノプリンホットケーキ６ティーバーコンマステスト","description":"ちいかわ、プリンの上に乗るうさぎを見つける！／ちいかわとうさぎの前に、巨大なホットケーキが…！","horizontal_thumbnail":"https://samba-laravel.s3.ap-northeast-1.amazonaws.com/vod/meta/thumbnail/UK6S6yhrh8pCR8NquDheqEL5fcE2BRuH03SnlbCu.jpg","genre_id":"anime","sub_genre_ids":["animal","health","kids"],"production_provider_id":{"network_id":"0x7FE4","service_id":"0x0420"},"onair_start_date":1649025600,"casts":[{"name":"青木遥","talent_id":""},{"name":"田中　誠人","talent_id":""},{"name":"小澤　亜李","talent_id":""},{"name":"井口　裕香","talent_id":""},{"name":"杉田　智和","talent_id":""},{"name":"東地　宏樹","talent_id":""},{"name":"松岡　禎丞","talent_id":""},{"name":"内田　雄馬","talent_id":""},{"name":"淺井　孝行","talent_id":""},{"name":"佐藤　隆太","talent_id":""},{"name":"岡田　義徳","talent_id":""},{"name":"塚本　高史","talent_id":""},{"name":"小林　大介","talent_id":""},{"name":"桃月　なしこ","talent_id":""},{"name":"安藤　玉恵","talent_id":""}],"staffs":[],"keywords":["動物","キッズ","ファミリー","めざましテレビ","癒し","ちいかわ","青木遥","ハチワレ","田中誠人","うさぎ","小澤亜李","モモンガ","井口裕香","ポシェットの鎧さん","杉田智和","労働の鎧さん","東地宏樹","ラーメンの鎧さん","松岡禎丞","ラッコ","内田雄馬","くりまんじゅう","淺井孝行"],"copyright":"（C）ナガノ／ちいかわ製作委員会","si_eventId":"","live_episode_key":"","division_ids":{"timing":["catchup"],"regular":["regular"],"kind":["main"],"sub_kind":[]},"number":10,"sub_number":1,"transcode_target":{"ovp":{"service":"videoCloud","owner":"tver"},"content":{"url":"https://mrss-content.s3.ap-northeast-1.amazonaws.com/5j00810001_avot_chiikawa_mezamashi_01_06.mp4","width":1920,"height":1080,"type":"video/mp4","filesize":0,"duration":92},"custom_field":[{"key":"tracking_id_01","value":"nr4c"},{"key":"tracking_id_02","value":"Fnr4cgp4b_fs2"},{"key":"tracking_id_03","value":"Fnr4cgp4b_fs2"}],"update_date":1654525232},"text_track":{"enable":false,"target":[],"update_date":0},"ad":{"server":"GoogleAdManager","type":"vmap","ad":{"ids":[{"key":"guid","value":"Fnr4cgp4b_fs2"}]}},"oaol":0,"svod_urls":[{"name":"fujitv","url":"https://fod.fujitv.co.jp/title/5j00/?waad=btYbqHRb\u0026ugad=btYbqHRb"}],"hashtags":["#ちいかわ"],"external_link":[{"link_type":"amazon","date":{"start":1649026800,"end":1735657140}},{"link_type":"google","date":{"start":1649026800,"end":1735657140}}],"disable":0,"publish_date":{"start":1649026800,"end":1735657140},"streaming_date":{"start":1649026800,"end":1735657140},"update_date":1720155914},{"episode_key":"Fnr4cf9mw_2h7","series_key":"xeh0","season_key":"nr4c","title":"第2話 スフィンクス／ほんものだ","title_kana":"チイカワ","description":"ちいかわとハチワレ、エジプトの本を読む／本物のスフィンクスが登場！？","horizontal_thumbnail":"https://mrss-content.s3.ap-northeast-1.amazonaws.com/episode_5j00810002.jpg","genre_id":"anime","sub_genre_ids":["animal","health","kids"],"production_provider_id":{"network_id":"0x7FE4","service_id":"0x0420"},"onair_start_date":1649371200,"casts":[{"name":"青木遥","talent_id":""},{"name":"田中　誠人","talent_id":""},{"name":"小澤　亜李","talent_id":""},{"name":"井口　裕香","talent_id":""},{"name":"杉田　智和","talent_id":""},{"name":"東地　宏樹","talent_id":""},{"name":"松岡　禎丞","talent_id":""},{"name":"内田　雄馬","talent_id":""},{"name":"淺井　孝行","talent_id":""}],"staffs":[],"keywords":["動物","キッズ","ファミリー","めざましテレビ","癒し","ちいかわ","青木遥","ハチワレ","田中誠人","うさぎ","小澤亜李","モモンガ","井口裕香","ポシェットの鎧さん","杉田智和","労働の鎧さん","東地宏樹","ラーメンの鎧さん","松岡禎丞","ラッコ","内田雄馬","くりまんじゅう","淺井孝行"],"copyright":"（C）ナガノ／ちいかわ製作委員会","si_eventId":"","live_episode_key":"","division_ids":{"timing":["catchup"],"regular":["regular"],"kind":["main"],"sub_kind":[]},"number":20,"sub_number":1,"transcode_target":{"ovp":{"service":"videoCloud","owner":"tver"},"content":{"url":"https://mrss-content.s3.ap-northeast-1.amazonaws.com/5j00810002_avot_chiikawa_mezamashi_02_06.mp4","width":1920,"height":1080,"type":"video/mp4","filesize":0,"duration":92},"custom_field":[{"key":"tracking_id_01","value":"nr4c"},{"key":"tracking_id_02","value":"Fnr4cf9mw_2h7"},{"key":"tracking_id_03","value":"Fnr4cf9mw_2h7"}],"update_date":1654525232},"text_track":{"enable":false,"target":[],"update_date":0},"ad":{"server":"GoogleAdManager","type":"vmap","ad":{"ids":[{"key":"guid","value":"Fnr4cf9mw_2h7"}]}},"oaol":0,"svod_urls":[{"name":"fujitv","url":"https://fod.fujitv.co.jp/title/5j00/?waad=btYbqHRb\u0026ugad=btYbqHRb"}],"hashtags":["#ちいかわ"],"external_link":[{"link_type":"amazon","date":{"start":1649372400,"end":1735657140}},{"link_type":"google","date":{"start":1649372400,"end":1735657140}}],"disable":0,"publish_date":{"start":1649372400,"end":1735657140},"streaming_date":{"start":1649372400,"end":1735657140},"update_date":1720155914},{"episode_key":"Fnr4c7eof_fmf","series_key":"xeh0","season_key":"nr4c","title":"第3話 イカ／パイシチュー","title_kana":"チイカワ","description":"ちいかわとうさぎがイカに！？／うさぎがパイシチューの中に落っこちた！？","horizontal_thumbnail":"https://mrss-content.s3.ap-northeast-1.amazonaws.com/episode_5j00810003.jpg","genre_id":"anime","sub_genre_ids":["animal","health","kids"],"production_provider_id":{"network_id":"0x7FE4","service_id":"0x0420"},"onair_start_date":1649976000,"casts":[{"name":"青木遥","talent_id":""},{"name":"田中　誠人","talent_id":""},{"name":"小澤　亜李","talent_id":""},{"name":"井口　裕香","talent_id":""},{"name":"杉田　智和","talent_id":""},{"name":"東地　宏樹","talent_id":""},{"name":"松岡　禎丞","talent_id":""},{"name":"内田　雄馬","talent_id":""},{"name":"淺井　孝行","talent_id":""}],"staffs":[],"keywords":["動物","キッズ","ファミリー","めざましテレビ","癒し","ちいかわ","青木遥","ハチワレ","田中誠人","うさぎ","小澤亜李","モモンガ","井口裕香","ポシェットの鎧さん","杉田智和","労働の鎧さん","東地宏樹","ラーメンの鎧さん","松岡禎丞","ラッコ","内田雄馬","くりまんじゅう","淺井孝行"],"copyright":"（C）ナガノ／ちいかわ製作委員会","si_eventId":"","live_episode_key":"","division_ids":{"timing":["catchup"],"regular":["regular"],"kind":["main"],"sub_kind":[]},"number":30,"sub_number":1,"transcode_target":{"ovp":{"service":"videoCloud","owner":"tver"},"content":{"url":"https://mrss-content.s3.ap-northeast-1.amazonaws.com/5j00810003_avot_chiikawa_mezamashi_03_06.mp4","width":1920,"height":1080,"type":"video/mp4","filesize":0,"duration":92},"custom_field":[{"key":"tracking_id_01","value":"nr4c"},{"key":"tracking_id_02","value":"Fnr4c7eof_fmf"},{"key":"tracking_id_03","value":"Fnr4c7eof_fmf"}],"update_date":1654525234},"text_track":{"enable":false,"target":[],"update_date":0},"ad":{"server":"GoogleAdManager","type":"vmap","ad":{"ids":[{"key":"guid","value":"Fnr4c7eof_fmf"}]}},"oaol":0,"svod_urls":[{"name":"fujitv","url":"https://fod.fujitv.co.jp/title/5j00/?waad=btYbqHRb\u0026ugad=btYbqHRb"}],"hashtags":["#ちいかわ"],"external_link":[{"link_type":"amazon","date":{"start":1649977200,"end":1735657140}},{"link_type":"google","date":{"start":1649977200,"end":1735657140}}],"disable":0,"publish_date":{"start":1649977200,"end":1735657140},"streaming_date":{"start":1649977200,"end":1735657140},"update_date":1720155914},{"episode_key":"Fnr4cat0g_3pr","series_key":"xeh0","season_key":"nr4c","title":"第4話 ブロッコリー／ピザまん","title_kana":"チイカワ","description":"ちいかわ、苦手なブロッコリーを克服？／ちいかわ、うさぎにピザまんをおねだり！","horizontal_thumbnail":"https://mrss-content.s3.ap-northeast-1.amazonaws.com/episode_5j00810004.jpg","genre_id":"anime","sub_genre_ids":["animal","health","kids"],"production_provider_id":{"network_id":"0x7FE4","service_id":"0x0420"},"onair_start_date":1650580800,"casts":[{"name":"青木遥","talent_id":""},{"name":"田中　誠人","talent_id":""},{"name":"小澤　亜李","talent_id":""},{"name":"井口　裕香","talent_id":""},{"name":"杉田　智和","talent_id":""},{"name":"東地　宏樹","talent_id":""},{"name":"松岡　禎丞","talent_id":""},{"name":"内田　雄馬","talent_id":""},{"name":"淺井　孝行","talent_id":""}],"staffs":[],"keywords":["動物","キッズ","ファミリー","めざましテレビ","癒し","ちいかわ","青木遥","ハチワレ","田中誠人","うさぎ","小澤亜李","モモンガ","井口裕香","ポシェットの鎧さん","杉田智和","労働の鎧さん","東地宏樹","ラーメンの鎧さん","松岡禎丞","ラッコ","内田雄馬","くりまんじゅう","淺井孝行"],"copyright":"（C）ナガノ／ちいかわ製作委員会","si_eventId":"","live_episode_key":"","division_ids":{"timing":["catchup"],"regular":["regular"],"kind":["main"],"sub_kind":[]},"number":40,"sub_number":1,"transcode_target":{"ovp":{"service":"videoCloud","owner":"tver"},"content":{"url":"https://mrss-content.s3.ap-northeast-1.amazonaws.com/5j00810004_avot_chiikawa_mezamashi_04_06.mp4","width":1920,"height":1080,"type":"video/mp4","filesize":0,"duration":92},"custom_field":[{"key":"tracking_id_01","value":"nr4c"},{"key":"tracking_id_02","value":"Fnr4cat0g_3pr"},{"key":"tracking_id_03","value":"Fnr4cat0g_3pr"}],"update_date":1654525234},"text_track":{"enable":false,"target":[],"update_date":0},"ad":{"server":"GoogleAdManager","type":"vmap","ad":{"ids":[{"key":"guid","value":"Fnr4cat0g_3pr"}]}},"oaol":0,"svod_urls":[{"name":"fujitv","url":"https://fod.fujitv.co.jp/title/5j00/?waad=btYbqHRb\u0026ugad=btYbqHRb"}],"hashtags":["#ちいかわ"],"external_link":[{"link_type":"amazon","date":{"start":1650582000,"end":1735657140}},{"link_type":"google","date":{"start":1650582000,"end":1735657140}}],"disable":0,"publish_date":{"start":1650582000,"end":1735657140},"streaming_date":{"start":1650582000,"end":1735657140},"update_date":1720155914},{"episode_key":"Fnr4cets4_yu1","series_key":"xeh0","season_key":"nr4c","title":"第5話 チャリメラ／チャルメラ","title_kana":"チイカワ","description":"ハチワレ、ちいかわにラーメンをごちそう！／ハチワレが赤面！？いったいなぜ…","horizontal_thumbnail":"https://mrss-content.s3.ap-northeast-1.amazonaws.com/episode_5j00810005.jpg","genre_id":"anime","sub_genre_ids":["animal","health","kids"],"production_provider_id":{"network_id":"0x7FE4","service_id":"0x0420"},"onair_start_date":1651185600,"casts":[{"name":"青木遥","talent_id":""},{"name":"田中　誠人","talent_id":""},{"name":"小澤　亜李","talent_id":""},{"name":"井口　裕香","talent_id":""},{"name":"杉田　智和","talent_id":""},{"name":"東地　宏樹","talent_id":""},{"name":"松岡　禎丞","talent_id":""},{"name":"内田　雄馬","talent_id":""},{"name":"淺井　孝行","talent_id":""}],"staffs":[],"keywords":["動物","キッズ","ファミリー","めざましテレビ","癒し","ちいかわ","青木遥","ハチワレ","田中誠人","うさぎ","小澤亜李","モモンガ","井口裕香","ポシェットの鎧さん","杉田智和","労働の鎧さん","東地宏樹","ラーメンの鎧さん","松岡禎丞","ラッコ","内田雄馬","くりまんじゅう","淺井孝行"],"copyright":"（C）ナガノ／ちいかわ製作委員会","si_eventId":"","live_episode_key":"","division_ids":{"timing":["catchup"],"regular":["regular"],"kind":["main"],"sub_kind":[]},"number":50,"sub_number":1,"transcode_target":{"ovp":{"service":"videoCloud","owner":"tver"},"content":{"url":"https://mrss-content.s3.ap-northeast-1.amazonaws.com/5j00810005_avot_chiikawa_mezamashi_05_06.mp4","width":1920,"height":1080,"type":"video/mp4","filesize":0,"duration":92},"custom_field":[{"key":"tracking_id_01","value":"nr4c"},{"key":"tracking_id_02","value":"Fnr4cets4_yu1"},{"key":"tracking_id_03","value":"Fnr4cets4_yu1"}],"update_date":1654525234},"text_track":{"enable":false,"target":[],"update_date":0},"ad":{"server":"GoogleAdManager","type":"vmap","ad":{"ids":[{"key":"guid","value":"Fnr4cets4_yu1"}]}},"oaol":0,"svod_urls":[{"name":"fujitv","url":"https://fod.fujitv.co.jp/title/5j00/?waad=btYbqHRb\u0026ugad=btYbqHRb"}],"hashtags":["#ちいかわ"],"external_link":[{"link_type":"amazon","date":{"start":1651186800,"end":1735657140}},{"link_type":"google","date":{"start":1651186800,"end":1735657140}}],"disable":0,"publish_date":{"start":1651186800,"end":1735657140},"streaming_date":{"start":1651186800,"end":1735657140},"update_date":1720155914},{"episode_key":"Fnr4cfo7u_rsq","series_key":"xeh0","season_key":"nr4c","title":"③リベンジ ⑧リベンジ　③ 既存シリーズ/シーズン配下に…（長いので手動でカットしました）","title_kana":"サンノリベンジ","description":"⑧リベンジ　\n③ 既存シリーズ/シーズン配下に新規エピソード追加（コンマス運用前から配信中シリーズのエピ追加想定）リベンジの内容","horizontal_thumbnail":"https://samba-laravel.s3.ap-northeast-1.amazonaws.com/vod/meta/thumbnail/rGmMY185NwxQRVXi2Rf5waKbyMegQGZWVPJ9jolP.jpg","genre_id":"anime","sub_genre_ids":["animal","health","kids"],"production_provider_id":{"network_id":"0x7FE4","service_id":"0x0420"},"onair_start_date":1713798000,"casts":[{"name":"青木遥","talent_id":""},{"name":"田中　誠人","talent_id":""},{"name":"小澤　亜李","talent_id":""},{"name":"井口　裕香","talent_id":""},{"name":"杉田　智和","talent_id":""},{"name":"東地　宏樹","talent_id":""},{"name":"松岡　禎丞","talent_id":""},{"name":"内田　雄馬","talent_id":""},{"name":"淺井　孝行","talent_id":""},{"name":"南　果歩","talent_id":""},{"name":"田口　トモロヲ","talent_id":""},{"name":"郭　智博","talent_id":""},{"name":"筒井　真理子","talent_id":""},{"name":"村上　淳","talent_id":""},{"name":"村上 淳","talent_id":""}],"staffs":[],"keywords":["⑧リベンジ　③リベンジ"],"copyright":"（C）ナガノ／ちいかわ製作委員会","si_eventId":"","live_episode_key":"","division_ids":{"timing":["catchup"],"regular":["regular"],"kind":["main"],"sub_kind":[]},"number":1480,"sub_number":1,"transcode_target":{"ovp":{"service":"videoCloud","owner":"tver"},"content":{"url":"https://mrss-content-step1-stg.s3.ap-northeast-1.amazonaws.com/Fnr4cfo7u_trhu.mp4","width":1920,"height":1080,"type":"video/mp4","filesize":0,"duration":301},"custom_field":[{"key":"tracking_id_01","value":"nr4c"},{"key":"tracking_id_02","value":"Fnr4cfo7u_rsq"},{"key":"tracking_id_03","value":"Fnr4cfo7u_rsq"}],"update_date":1715133673},"text_track":{"enable":false,"target":[],"update_date":0},"ad":{"server":"GoogleAdManager","type":"vmap","ad":{"ids":[{"key":"guid","value":"Fnr4cfo7u_rsq"}]}},"oaol":0,"svod_urls":[{"name":"fujitv","url":"https://fod.fujitv.co.jp/title/5j00/?waad=btYbqHRb\u0026ugad=btYbqHRb"}],"hashtags":["#③リベンジ"],"external_link":[{"link_type":"amazon","date":{"start":1713841200,"end":4102412340}},{"link_type":"google","date":{"start":1713841200,"end":4102412340}}],"disable":0,"publish_date":{"start":1713841200,"end":4102412340},"streaming_date":{"start":1713841200,"end":4102412340},"update_date":1720155914},{"episode_key":"Fm5r83z65_j3m","series_key":"r4ge","season_key":"m5r8","title":"前倒し確認（登録） ","title_kana":"ランチ ノ ジョウオウ","description":"【山下智久主演 水10ドラマ『ブルーモーメント』2024年4月スタート！】\n【『フジドラSPRING！』開催！フジテレビ名作ドラマをTVer・FODで続々配信！】\n【毎週日曜に最新話配信】\n★お気に入り登録で最新話を見逃さない！★\n\n【FODプレミアムでは『ランチの女王』を全話配信中！名作ドラマを“イッキ見”できる！】","horizontal_thumbnail":"","genre_id":"drama","sub_genre_ids":["family","gourmet","romance"],"production_provider_id":{"network_id":"0x7FE4","service_id":"0x0420"},"onair_start_date":1717167600,"casts":[{"name":"竹内　結子","talent_id":""},{"name":"妻夫木　聡","talent_id":""},{"name":"伊東　美咲","talent_id":""},{"name":"山下　智久","talent_id":""},{"name":"山田　孝之","talent_id":""},{"name":"若林　豪","talent_id":""},{"name":"堤　真一","talent_id":""},{"name":"江口　洋介","talent_id":""},{"name":"永山　瑛太","talent_id":""}],"staffs":[],"keywords":["洋食","ランチ","おいしいもの","デミグラスソース","オムライス","キッチンマカロニ","兄弟","恋愛","婚約者","家族","嘘","ホームコメディ","竹内結子","妻夫木聡","伊東美咲","山下智久","山田孝之","EITA","瑛太","梅宮万紗子","田窪一世","鈴木えみ","若林豪","堤真一","江口洋介","森田剛","佐藤江梨子","岡田浩暉","モロ師岡","桐谷健太","上地雄輔","石黒賢"],"copyright":"（C）フジテレビ","si_eventId":"","live_episode_key":"","division_ids":{"timing":["archive"],"regular":["regular"],"kind":["main"],"sub_kind":[]},"number":30,"sub_number":1,"transcode_target":{"ovp":{"service":"videoCloud","owner":"tver"},"content":{"url":"","width":1920,"height":1080,"type":"video/mp4","filesize":0,"duration":0},"custom_field":[{"key":"tracking_id_01","value":"m5r8"},{"key":"tracking_id_02","value":"Fm5r83z65_j3m"},{"key":"tracking_id_03","value":"Fm5r83z65_j3m"}],"update_date":1717585146},"text_track":{"enable":false,"target":[],"update_date":0},"ad":{"server":"GoogleAdManager","type":"vmap","ad":{"ids":[{"key":"guid","value":"Fm5r83z65_j3m"}]}},"oaol":0,"svod_urls":[{"name":"fujitv","url":"https://fod.fujitv.co.jp/title/g9vz?waad=iiKggdsF\u0026ugad=iiKggdsF"}],"hashtags":["#【開発者テスト】ランチの女王"],"external_link":[{"link_type":"amazon","date":{"start":1717167600,"end":1725116340}},{"link_type":"google","date":{"start":1717167600,"end":1725116340}}],"disable":0,"publish_date":{"start":1717167600,"end":1725116340},"streaming_date":{"start":1717167600,"end":1725116340},"update_date":1719902695},{"episode_key":"Fm5r8dov9_how","series_key":"r4ge","season_key":"m5r8","title":"前倒し確認（一括） ","title_kana":"ランチ ノ ジョウオウ","description":"【山下智久主演 水10ドラマ『ブルーモーメント』2024年4月スタート！】\n【『フジドラSPRING！』開催！フジテレビ名作ドラマをTVer・FODで続々配信！】\n【毎週日曜に最新話配信】\n★お気に入り登録で最新話を見逃さない！★\n\n【FODプレミアムでは『ランチの女王』を全話配信中！名作ドラマを“イッキ見”できる！】","horizontal_thumbnail":"","genre_id":"drama","sub_genre_ids":["family","gourmet","romance"],"production_provider_id":{"network_id":"0x7FE4","service_id":"0x0420"},"onair_start_date":1717167600,"casts":[{"name":"竹内　結子","talent_id":""},{"name":"妻夫木　聡","talent_id":""},{"name":"伊東　美咲","talent_id":""},{"name":"山下　智久","talent_id":""},{"name":"山田　孝之","talent_id":""},{"name":"若林　豪","talent_id":""},{"name":"堤　真一","talent_id":""},{"name":"江口　洋介","talent_id":""},{"name":"永山　瑛太","talent_id":""}],"staffs":[],"keywords":["洋食","ランチ","おいしいもの","デミグラスソース","オムライス","キッチンマカロニ","兄弟","恋愛","婚約者","家族","嘘","ホームコメディ","竹内結子","妻夫木聡","伊東美咲","山下智久","山田孝之","EITA","瑛太","梅宮万紗子","田窪一世","鈴木えみ","若林豪","堤真一","江口洋介","森田剛","佐藤江梨子","岡田浩暉","モロ師岡","桐谷健太","上地雄輔","石黒賢"],"copyright":"（C）フジテレビ","si_eventId":"","live_episode_key":"","division_ids":{"timing":["archive"],"regular":["regular"],"kind":["main"],"sub_kind":[]},"number":40,"sub_number":1,"transcode_target":{"ovp":{"service":"videoCloud","owner":"tver"},"content":{"url":"","width":1920,"height":1080,"type":"video/mp4","filesize":0,"duration":0},"custom_field":[{"key":"tracking_id_01","value":"m5r8"},{"key":"tracking_id_02","value":"Fm5r8dov9_how"},{"key":"tracking_id_03","value":"Fm5r8dov9_how"}],"update_date":1717585146},"text_track":{"enable":false,"target":[],"update_date":0},"ad":{"server":"GoogleAdManager","type":"vmap","ad":{"ids":[{"key":"guid","value":"Fm5r8dov9_how"}]}},"oaol":0,"svod_urls":[{"name":"fujitv","url":"https://fod.fujitv.co.jp/title/g9vz?waad=iiKggdsF\u0026ugad=iiKggdsF"}],"hashtags":["#【開発者テスト】ランチの女王"],"external_link":[{"link_type":"amazon","date":{"start":1717167600,"end":1725116340}},{"link_type":"google","date":{"start":1717167600,"end":1725116340}}],"disable":0,"publish_date":{"start":1717167600,"end":1725116340},"streaming_date":{"start":1717167600,"end":1725116340},"update_date":1719902700},{"episode_key":"Fm5r8pxoz_9ta","series_key":"r4ge","season_key":"m5r8","title":"ｆ ","title_kana":"ランチ ノ ジョウオウ","description":"【山下智久主演 水10ドラマ『ブルーモーメント』2024年4月スタート！】\n【『フジドラSPRING！』開催！フジテレビ名作ドラマをTVer・FODで続々配信！】\n【毎週日曜に最新話配信】\n★お気に入り登録で最新話を見逃さない！★\n\n【FODプレミアムでは『ランチの女王』を全話配信中！名作ドラマを“イッキ見”できる！】","horizontal_thumbnail":"","genre_id":"drama","sub_genre_ids":["family","gourmet","romance"],"production_provider_id":{"network_id":"0x7FE4","service_id":"0x0420"},"onair_start_date":1721228400,"casts":[{"name":"竹内　結子","talent_id":""},{"name":"妻夫木　聡","talent_id":""},{"name":"伊東　美咲","talent_id":""},{"name":"山下　智久","talent_id":""},{"name":"山田　孝之","talent_id":""},{"name":"若林　豪","talent_id":""},{"name":"堤　真一","talent_id":""},{"name":"江口　洋介","talent_id":""},{"name":"永山　瑛太","talent_id":""}],"staffs":[],"keywords":["洋食","ランチ","おいしいもの","デミグラスソース","オムライス","キッチンマカロニ","兄弟","恋愛","婚約者","家族","嘘","ホームコメディ","竹内結子","妻夫木聡","伊東美咲","山下智久","山田孝之","EITA","瑛太","梅宮万紗子","田窪一世","鈴木えみ","若林豪","堤真一","江口洋介","森田剛","佐藤江梨子","岡田浩暉","モロ師岡","桐谷健太","上地雄輔","石黒賢"],"copyright":"（C）フジテレビ","si_eventId":"","live_episode_key":"","division_ids":{"timing":["archive"],"regular":["regular"],"kind":["main"],"sub_kind":[]},"number":150,"sub_number":1,"transcode_target":{"ovp":{"service":"videoCloud","owner":"tver"},"content":{"url":"","width":1920,"height":1080,"type":"video/mp4","filesize":0,"duration":0},"custom_field":[{"key":"tracking_id_01","value":"m5r8"},{"key":"tracking_id_02","value":"Fm5r8pxoz_9ta"},{"key":"tracking_id_03","value":"Fm5r8pxoz_9ta"}],"update_date":1719929276},"text_track":{"enable":false,"target":[],"update_date":0},"ad":{"server":"GoogleAdManager","type":"vmap","ad":{"ids":[{"key":"guid","value":"Fm5r8pxoz_9ta"}]}},"oaol":0,"svod_urls":[{"name":"fujitv","url":"https://fod.fujitv.co.jp/title/g9vz?waad=iiKggdsF\u0026ugad=iiKggdsF"}],"hashtags":["#【開発者テスト】ランチの女王"],"external_link":[{"link_type":"amazon","date":{"start":1721228400,"end":4102412340}},{"link_type":"google","date":{"start":1721228400,"end":4102412340}}],"disable":0,"publish_date":{"start":1721228400,"end":4102412340},"streaming_date":{"start":1721228400,"end":4102412340},"update_date":1719929388},{"episode_key":"Fm5r89ovt_jq2","series_key":"r4ge","season_key":"m5r8","title":"VMAPツール（新規・FODTVer） ","title_kana":"ランチ ノ ジョウオウ","description":"【山下智久主演 水10ドラマ『ブルーモーメント』2024年4月スタート！】\n【『フジドラSPRING！』開催！フジテレビ名作ドラマをTVer・FODで続々配信！】\n【毎週日曜に最新話配信】\n★お気に入り登録で最新話を見逃さない！★\n\n【FODプレミアムでは『ランチの女王』を全話配信中！名作ドラマを“イッキ見”できる！】","horizontal_thumbnail":"https://samba-laravel.s3.ap-northeast-1.amazonaws.com/vod/meta/thumbnail/hEYxxYMj6vBGEOyicCsjjIFnBFDGR5d6dJcBUijJ.png","genre_id":"drama","sub_genre_ids":["family","gourmet","romance"],"production_provider_id":{"network_id":"0x7FE4","service_id":"0x0420"},"onair_start_date":1721228400,"casts":[{"name":"竹内　結子","talent_id":""},{"name":"妻夫木　聡","talent_id":""},{"name":"伊東　美咲","talent_id":""},{"name":"山下　智久","talent_id":""},{"name":"山田　孝之","talent_id":""},{"name":"若林　豪","talent_id":""},{"name":"堤　真一","talent_id":""},{"name":"江口　洋介","talent_id":""},{"name":"永山　瑛太","talent_id":""}],"staffs":[],"keywords":["洋食","ランチ","おいしいもの","デミグラスソース","オムライス","キッチンマカロニ","兄弟","恋愛","婚約者","家族","嘘","ホームコメディ","竹内結子","妻夫木聡","伊東美咲","山下智久","山田孝之","EITA","瑛太","梅宮万紗子","田窪一世","鈴木えみ","若林豪","堤真一","江口洋介","森田剛","佐藤江梨子","岡田浩暉","モロ師岡","桐谷健太","上地雄輔","石黒賢"],"copyright":"（C）フジテレビ","si_eventId":"","live_episode_key":"","division_ids":{"timing":["archive"],"regular":["regular"],"kind":["main"],"sub_kind":[]},"number":190,"sub_number":1,"transcode_target":{"ovp":{"service":"videoCloud","owner":"tver"},"content":{"url":"https://mrss-content-step1-stg.s3.ap-northeast-1.amazonaws.com/Fm5r89ovt_sgyl.mp4","width":1920,"height":1080,"type":"video/mp4","filesize":0,"duration":2},"custom_field":[{"key":"tracking_id_01","value":"m5r8"},{"key":"tracking_id_02","value":"Fm5r89ovt_jq2"},{"key":"tracking_id_03","value":"Fm5r89ovt_jq2"}],"update_date":1719983600},"text_track":{"enable":false,"target":[],"update_date":0},"ad":{"server":"GoogleAdManager","type":"vmap","ad":{"ids":[{"key":"guid","value":"Fm5r89ovt_jq2"}]}},"oaol":0,"svod_urls":[{"name":"fujitv","url":"https://fod.fujitv.co.jp/title/g9vz?waad=iiKggdsF\u0026ugad=iiKggdsF"}],"hashtags":["#【開発者テスト】ランチの女王"],"external_link":[{"link_type":"amazon","date":{"start":1721228400,"end":4102412340}},{"link_type":"google","date":{"start":1721228400,"end":4102412340}}],"disable":0,"publish_date":{"start":1721228400,"end":4102412340},"streaming_date":{"start":1721228400,"end":4102412340},"update_date":1719984105}]